xialib_bigquery/__init__.py
xialib_bigquery/bigquery_adaptor.py
xialib_bigquery-0.1.0.dist-info/LICENSE
xialib_bigquery-0.1.0.dist-info/METADATA
xialib_bigquery-0.1.0.dist-info/WHEEL
xialib_bigquery-0.1.0.dist-info/top_level.txt
xialib_bigquery-0.1.0.dist-info/RECORD
